i3_screen_util/__init__.py
i3_screen_util/args.py
i3_screen_util/lockscreen.py
i3_screen_util/monitor_controller.py
i3_screen_util/process_manager.py
i3_screen_util/screenkey.py
i3_screen_util/workspace_formatter.py
i3_screen_util/bin/control-lockscreen.sh
i3_screen_util/bin/load-workspaces.sh
i3_screen_util/bin/save-workspaces.sh
i3_screen_util-0.2.3.data/scripts/control-lockscreen.sh
i3_screen_util-0.2.3.data/scripts/load-workspaces.sh
i3_screen_util-0.2.3.data/scripts/save-workspaces.sh
i3_screen_util-0.2.3.dist-info/LICENSE
i3_screen_util-0.2.3.dist-info/METADATA
i3_screen_util-0.2.3.dist-info/WHEEL
i3_screen_util-0.2.3.dist-info/entry_points.txt
i3_screen_util-0.2.3.dist-info/top_level.txt
i3_screen_util-0.2.3.dist-info/RECORD
