Metadata-Version: 2.1
Name: i3-screen-util
Version: 0.2.3
Summary: A screen management tool for your lovely i3wm config.
Author-email: Can Vardar <ismailcanvardar@gmail.com>
License: MIT License
Project-URL: Homepage, https://github.com/icanvardar/i3-screen-util
Project-URL: Issues, https://github.com/icanvardar/i3-screen-util/issues
Classifier: Programming Language :: Python :: 3
Classifier: License :: OSI Approved :: MIT License
Classifier: Operating System :: OS Independent
Requires-Python: >=3.10
License-File: LICENSE
